LICENSE
README.rst
check_pipfile_lock.py
pyproject.toml
setup.cfg
setup.py
check_pipfile_lock.egg-info/PKG-INFO
check_pipfile_lock.egg-info/SOURCES.txt
check_pipfile_lock.egg-info/dependency_links.txt
check_pipfile_lock.egg-info/entry_points.txt
check_pipfile_lock.egg-info/requires.txt
check_pipfile_lock.egg-info/top_level.txt