Metadata-Version: 1.1
Name: check-pipfile-lock
Version: 0.0.4
Summary: Check pipenv's Pipfile.lock to be consistent with Pipfile
Home-page: https://github.com/haizaar/check-pipfile-lock
Author: Zaar Hai
Author-email: haizaar@haizaar.com
License: MIT License
